notifier/__init__.py
notifier/discord_notifier.py
cgraaaj_discord_notifier-0.1.0.dist-info/METADATA
cgraaaj_discord_notifier-0.1.0.dist-info/WHEEL
cgraaaj_discord_notifier-0.1.0.dist-info/top_level.txt
cgraaaj_discord_notifier-0.1.0.dist-info/RECORD
